{
    "nome": [
        [
            2082,
            0.47712125471966244
        ],
        [
            2604,
            0.6989700043360189
        ]
    ],
    "nomenclatur": [
        [
            846,
            0.3010299956639812
        ],
        [
            1029,
            0.3010299956639812
        ],
        [
            2604,
            0.6989700043360189
        ]
    ],
    "nomi": [
        [
            1639,
            0.47712125471966244
        ],
        [
            1660,
            0.47712125471966244
        ],
        [
            1963,
            0.3010299956639812
        ],
        [
            2140,
            0.3010299956639812
        ],
        [
            2499,
            0.3010299956639812
        ],
        [
            2604,
            1.2304489213782739
        ]
    ],
    "nomic": [
        [
            1140,
            0.3010299956639812
        ],
        [
            2604,
            0.47712125471966244
        ]
    ],
    "nomin": [
        [
            184,
            0.3010299956639812
        ],
        [
            387,
            0.3010299956639812
        ],
        [
            477,
            0.3010299956639812
        ],
        [
            573,
            0.3010299956639812
        ],
        [
            597,
            0.47712125471966244
        ],
        [
            599,
            0.3010299956639812
        ],
        [
            600,
            0.6989700043360189
        ],
        [
            639,
            0.3010299956639812
        ],
        [
            659,
            0.47712125471966244
        ],
        [
            736,
            0.3010299956639812
        ],
        [
            758,
            0.6989700043360189
        ],
        [
            801,
            0.3010299956639812
        ],
        [
            804,
            0.3010299956639812
        ],
        [
            806,
            0.6020599913279624
        ],
        [
            816,
            0.3010299956639812
        ],
        [
            870,
            0.6989700043360189
        ],
        [
            888,
            0.3010299956639812
        ],
        [
            939,
            0.3010299956639812
        ],
        [
            1009,
            0.3010299956639812
        ],
        [
            1021,
            0.3010299956639812
        ],
        [
            1033,
            0.3010299956639812
        ],
        [
            1040,
            0.3010299956639812
        ],
        [
            1045,
            0.6020599913279624
        ],
        [
            1065,
            0.3010299956639812
        ],
        [
            1068,
            0.3010299956639812
        ],
        [
            1097,
            0.3010299956639812
        ],
        [
            1146,
            0.3010299956639812
        ],
        [
            1148,
            0.47712125471966244
        ],
        [
            1153,
            0.47712125471966244
        ],
        [
            1182,
            0.47712125471966244
        ],
        [
            1206,
            0.3010299956639812
        ],
        [
            1209,
            0.3010299956639812
        ],
        [
            1249,
            0.3010299956639812
        ],
        [
            1260,
            0.3010299956639812
        ],
        [
            1376,
            0.8450980400142568
        ],
        [
            1425,
            0.6020599913279624
        ],
        [
            1435,
            0.6020599913279624
        ],
        [
            1473,
            0.8450980400142568
        ],
        [
            1476,
            0.3010299956639812
        ],
        [
            1493,
            0.47712125471966244
        ],
        [
            1543,
            0.6989700043360189
        ],
        [
            1559,
            0.3010299956639812
        ],
        [
            1590,
            0.3010299956639812
        ],
        [
            1593,
            0.47712125471966244
        ],
        [
            1605,
            0.3010299956639812
        ],
        [
            1727,
            0.3010299956639812
        ],
        [
            1769,
            0.3010299956639812
        ],
        [
            1782,
            0.9542425094393249
        ],
        [
            1817,
            0.3010299956639812
        ],
        [
            1835,
            0.3010299956639812
        ],
        [
            1836,
            0.3010299956639812
        ],
        [
            1846,
            0.3010299956639812
        ],
        [
            1852,
            0.3010299956639812
        ],
        [
            1881,
            0.6020599913279624
        ],
        [
            1890,
            0.3010299956639812
        ],
        [
            1907,
            0.47712125471966244
        ],
        [
            1960,
            0.3010299956639812
        ],
        [
            1972,
            0.3010299956639812
        ],
        [
            2012,
            0.3010299956639812
        ],
        [
            2042,
            0.3010299956639812
        ],
        [
            2079,
            1.1139433523068367
        ],
        [
            2162,
            0.47712125471966244
        ],
        [
            2182,
            0.3010299956639812
        ],
        [
            2188,
            0.47712125471966244
        ],
        [
            2201,
            0.3010299956639812
        ],
        [
            2221,
            0.3010299956639812
        ],
        [
            2227,
            0.3010299956639812
        ],
        [
            2255,
            0.47712125471966244
        ],
        [
            2260,
            0.3010299956639812
        ],
        [
            2278,
            0.3010299956639812
        ],
        [
            2291,
            1.2041199826559248
        ],
        [
            2332,
            0.3010299956639812
        ],
        [
            2343,
            0.3010299956639812
        ],
        [
            2349,
            0.3010299956639812
        ],
        [
            2353,
            0.3010299956639812
        ],
        [
            2379,
            0.3010299956639812
        ],
        [
            2402,
            0.6020599913279624
        ],
        [
            2403,
            0.3010299956639812
        ],
        [
            2412,
            0.3010299956639812
        ],
        [
            2455,
            0.3010299956639812
        ],
        [
            2475,
            0.6989700043360189
        ],
        [
            2517,
            0.3010299956639812
        ],
        [
            2532,
            0.3010299956639812
        ],
        [
            2545,
            0.3010299956639812
        ],
        [
            2604,
            2.537819095073274
        ]
    ],
    "nomina": [
        [
            639,
            0.47712125471966244
        ],
        [
            1472,
            0.3010299956639812
        ],
        [
            2604,
            0.8450980400142568
        ]
    ],
    "nominal": [
        [
            2604,
            0.47712125471966244
        ]
    ],
    "nominali": [
        [
            1818,
            0.3010299956639812
        ],
        [
            2604,
            0.47712125471966244
        ]
    ],
    "nominalis": [
        [
            1000,
            0.3010299956639812
        ],
        [
            2604,
            0.6989700043360189
        ]
    ],
    "nominalkomposita": [
        [
            1847,
            0.3010299956639812
        ],
        [
            2010,
            0.3010299956639812
        ],
        [
            2604,
            0.6989700043360189
        ]
    ],
    "nominalsdtz": [
        [
            1765,
            0.3010299956639812
        ],
        [
            2604,
            0.47712125471966244
        ]
    ],
    "nominanda": [
        [
            2604,
            0.47712125471966244
        ]
    ],
    "nominative-accus": [
        [
            1747,
            0.3010299956639812
        ],
        [
            1881,
            0.3010299956639812
        ],
        [
            2604,
            0.6989700043360189
        ]
    ],
    "nomo": [
        [
            1556,
            0.3010299956639812
        ],
        [
            1570,
            0.3010299956639812
        ],
        [
            2604,
            0.6989700043360189
        ]
    ],
    "nomoto": [
        [
            883,
            0.3010299956639812
        ],
        [
            1559,
            0.3010299956639812
        ],
        [
            2604,
            0.6989700043360189
        ]
    ],
    "non": [
        [
            56,
            0.3010299956639812
        ],
        [
            60,
            0.47712125471966244
        ],
        [
            115,
            0.47712125471966244
        ],
        [
            117,
            0.47712125471966244
        ],
        [
            145,
            0.3010299956639812
        ],
        [
            190,
            0.6020599913279624
        ],
        [
            318,
            0.3010299956639812
        ],
        [
            375,
            0.3010299956639812
        ],
        [
            461,
            0.3010299956639812
        ],
        [
            476,
            0.3010299956639812
        ],
        [
            530,
            0.3010299956639812
        ],
        [
            531,
            0.3010299956639812
        ],
        [
            577,
            0.3010299956639812
        ],
        [
            589,
            0.3010299956639812
        ],
        [
            599,
            0.3010299956639812
        ],
        [
            658,
            0.47712125471966244
        ],
        [
            673,
            0.3010299956639812
        ],
        [
            678,
            0.3010299956639812
        ],
        [
            720,
            0.3010299956639812
        ],
        [
            724,
            0.3010299956639812
        ],
        [
            744,
            0.3010299956639812
        ],
        [
            877,
            0.3010299956639812
        ],
        [
            906,
            0.3010299956639812
        ],
        [
            914,
            0.3010299956639812
        ],
        [
            1005,
            0.3010299956639812
        ],
        [
            1009,
            0.3010299956639812
        ],
        [
            1029,
            0.3010299956639812
        ],
        [
            1033,
            0.3010299956639812
        ],
        [
            1056,
            0.3010299956639812
        ],
        [
            1060,
            0.3010299956639812
        ],
        [
            1069,
            0.3010299956639812
        ],
        [
            1099,
            0.3010299956639812
        ],
        [
            1126,
            0.3010299956639812
        ],
        [
            1131,
            0.47712125471966244
        ],
        [
            1140,
            0.3010299956639812
        ],
        [
            1146,
            0.3010299956639812
        ],
        [
            1147,
            0.3010299956639812
        ],
        [
            1148,
            0.3010299956639812
        ],
        [
            1152,
            0.3010299956639812
        ],
        [
            1156,
            0.3010299956639812
        ],
        [
            1180,
            0.47712125471966244
        ],
        [
            1188,
            0.3010299956639812
        ],
        [
            1196,
            0.3010299956639812
        ],
        [
            1198,
            0.3010299956639812
        ],
        [
            1214,
            0.3010299956639812
        ],
        [
            1261,
            0.3010299956639812
        ],
        [
            1268,
            0.3010299956639812
        ],
        [
            1269,
            0.3010299956639812
        ],
        [
            1271,
            0.3010299956639812
        ],
        [
            1292,
            0.6989700043360189
        ],
        [
            1314,
            0.3010299956639812
        ],
        [
            1331,
            0.47712125471966244
        ],
        [
            1352,
            0.6020599913279624
        ],
        [
            1362,
            0.3010299956639812
        ],
        [
            1364,
            0.3010299956639812
        ],
        [
            1378,
            0.3010299956639812
        ],
        [
            1385,
            0.47712125471966244
        ],
        [
            1396,
            0.3010299956639812
        ],
        [
            1405,
            0.3010299956639812
        ],
        [
            1414,
            0.3010299956639812
        ],
        [
            1437,
            0.3010299956639812
        ],
        [
            1444,
            0.47712125471966244
        ],
        [
            1453,
            0.3010299956639812
        ],
        [
            1458,
            0.3010299956639812
        ],
        [
            1472,
            0.3010299956639812
        ],
        [
            1519,
            0.3010299956639812
        ],
        [
            1542,
            0.3010299956639812
        ],
        [
            1548,
            0.3010299956639812
        ],
        [
            1549,
            0.3010299956639812
        ],
        [
            1550,
            0.3010299956639812
        ],
        [
            1551,
            0.3010299956639812
        ],
        [
            1560,
            0.47712125471966244
        ],
        [
            1561,
            0.3010299956639812
        ],
        [
            1564,
            0.3010299956639812
        ],
        [
            1569,
            0.3010299956639812
        ],
        [
            1582,
            0.3010299956639812
        ],
        [
            1584,
            0.3010299956639812
        ],
        [
            1594,
            0.6020599913279624
        ],
        [
            1599,
            0.3010299956639812
        ],
        [
            1602,
            0.6020599913279624
        ],
        [
            1608,
            0.3010299956639812
        ],
        [
            1627,
            0.6020599913279624
        ],
        [
            1656,
            0.3010299956639812
        ],
        [
            1666,
            0.3010299956639812
        ],
        [
            1673,
            0.6020599913279624
        ],
        [
            1680,
            0.47712125471966244
        ],
        [
            1699,
            0.3010299956639812
        ],
        [
            1705,
            0.47712125471966244
        ],
        [
            1737,
            0.3010299956639812
        ],
        [
            1755,
            0.3010299956639812
        ],
        [
            1772,
            0.3010299956639812
        ],
        [
            1776,
            0.3010299956639812
        ],
        [
            1811,
            0.3010299956639812
        ],
        [
            1817,
            0.3010299956639812
        ],
        [
            1834,
            0.3010299956639812
        ],
        [
            1836,
            0.3010299956639812
        ],
        [
            1842,
            0.3010299956639812
        ],
        [
            1846,
            0.3010299956639812
        ],
        [
            1852,
            0.3010299956639812
        ],
        [
            1861,
            0.6020599913279624
        ],
        [
            1869,
            0.3010299956639812
        ],
        [
            1907,
            0.3010299956639812
        ],
        [
            1908,
            0.3010299956639812
        ],
        [
            1930,
            0.3010299956639812
        ],
        [
            1941,
            0.47712125471966244
        ],
        [
            1943,
            0.3010299956639812
        ],
        [
            1952,
            0.47712125471966244
        ],
        [
            1956,
            0.3010299956639812
        ],
        [
            1960,
            0.3010299956639812
        ],
        [
            2007,
            0.3010299956639812
        ],
        [
            2024,
            0.3010299956639812
        ],
        [
            2081,
            0.3010299956639812
        ],
        [
            2082,
            0.47712125471966244
        ],
        [
            2094,
            0.47712125471966244
        ],
        [
            2096,
            0.47712125471966244
        ],
        [
            2119,
            0.3010299956639812
        ],
        [
            2130,
            0.3010299956639812
        ],
        [
            2132,
            0.3010299956639812
        ],
        [
            2138,
            0.3010299956639812
        ],
        [
            2145,
            0.3010299956639812
        ],
        [
            2150,
            0.47712125471966244
        ],
        [
            2188,
            0.6020599913279624
        ],
        [
            2238,
            0.3010299956639812
        ],
        [
            2257,
            0.7781512503836436
        ],
        [
            2258,
            0.3010299956639812
        ],
        [
            2280,
            0.6020599913279624
        ],
        [
            2287,
            0.3010299956639812
        ],
        [
            2294,
            0.3010299956639812
        ],
        [
            2332,
            0.47712125471966244
        ],
        [
            2365,
            0.3010299956639812
        ],
        [
            2387,
            0.3010299956639812
        ],
        [
            2403,
            0.3010299956639812
        ],
        [
            2424,
            0.47712125471966244
        ],
        [
            2435,
            0.47712125471966244
        ],
        [
            2439,
            0.3010299956639812
        ],
        [
            2475,
            0.3010299956639812
        ],
        [
            2477,
            0.3010299956639812
        ],
        [
            2478,
            0.3010299956639812
        ],
        [
            2492,
            0.3010299956639812
        ],
        [
            2510,
            0.47712125471966244
        ],
        [
            2514,
            0.3010299956639812
        ],
        [
            2516,
            0.3010299956639812
        ],
        [
            2527,
            0.3010299956639812
        ],
        [
            2604,
            2.611723308007342
        ]
    ],
    "non-absolut": [
        [
            827,
            0.3010299956639812
        ],
        [
            2604,
            0.47712125471966244
        ]
    ],
    "non-accedit": [
        [
            235,
            0.3010299956639812
        ],
        [
            2604,
            0.47712125471966244
        ]
    ],
    "non-accredit": [
        [
            234,
            0.3010299956639812
        ],
        [
            238,
            0.3010299956639812
        ],
        [
            2604,
            0.6989700043360189
        ]
    ],
    "non-affect": [
        [
            2255,
            0.3010299956639812
        ],
        [
            2604,
            0.47712125471966244
        ]
    ],
    "non-affr": [
        [
            1302,
            0.3010299956639812
        ],
        [
            2604,
            0.47712125471966244
        ]
    ],
    "non-alcohol": [
        [
            387,
            0.3010299956639812
        ],
        [
            2604,
            0.47712125471966244
        ]
    ],
    "non-ambigu": [
        [
            2604,
            0.47712125471966244
        ]
    ],
    "non-analyt": [
        [
            2172,
            0.3010299956639812
        ],
        [
            2207,
            0.3010299956639812
        ],
        [
            2604,
            0.6989700043360189
        ]
    ],
    "non-anonym": [
        [
            2202,
            0.3010299956639812
        ],
        [
            2604,
            0.47712125471966244
        ]
    ],
    "non-arbitrari": [
        [
            765,
            0.3010299956639812
        ],
        [
            1320,
            0.3010299956639812
        ],
        [
            2604,
            0.6989700043360189
        ]
    ],
    "non-arbitrarili": [
        [
            599,
            0.3010299956639812
        ],
        [
            2604,
            0.47712125471966244
        ]
    ],
    "non-aryan": [
        [
            1550,
            0.3010299956639812
        ],
        [
            2604,
            0.47712125471966244
        ]
    ],
    "non-attend": [
        [
            1861,
            0.3010299956639812
        ],
        [
            2604,
            0.47712125471966244
        ]
    ],
    "non-autonom": [
        [
            1826,
            0.3010299956639812
        ],
        [
            2604,
            0.47712125471966244
        ]
    ],
    "non-buy": [
        [
            368,
            0.3010299956639812
        ],
        [
            379,
            0.3010299956639812
        ],
        [
            2604,
            0.6989700043360189
        ]
    ],
    "non-canon": [
        [
            2440,
            0.3010299956639812
        ],
        [
            2604,
            0.6989700043360189
        ]
    ],
    "non-caus": [
        [
            1874,
            0.3010299956639812
        ],
        [
            2604,
            0.47712125471966244
        ]
    ],
    "non-citizen": [
        [
            1064,
            0.3010299956639812
        ],
        [
            2604,
            0.47712125471966244
        ]
    ],
    "non-class": [
        [
            1973,
            0.3010299956639812
        ],
        [
            2604,
            0.47712125471966244
        ]
    ],
    "non-commerci": [
        [
            92,
            0.3010299956639812
        ],
        [
            113,
            0.3010299956639812
        ],
        [
            155,
            0.3010299956639812
        ],
        [
            241,
            0.3010299956639812
        ],
        [
            246,
            0.3010299956639812
        ],
        [
            265,
            0.3010299956639812
        ],
        [
            312,
            0.3010299956639812
        ],
        [
            353,
            0.3010299956639812
        ],
        [
            1479,
            0.3010299956639812
        ],
        [
            2336,
            0.3010299956639812
        ],
        [
            2604,
            1.3222192947339193
        ]
    ],
    "non-complet": [
        [
            1560,
            0.3010299956639812
        ],
        [
            2177,
            0.3010299956639812
        ],
        [
            2604,
            0.6989700043360189
        ]
    ],
    "non-configur": [
        [
            1784,
            0.3010299956639812
        ],
        [
            2075,
            0.3010299956639812
        ],
        [
            2604,
            0.6989700043360189
        ]
    ],
    "non-constitu": [
        [
            2019,
            0.3010299956639812
        ],
        [
            2063,
            0.3010299956639812
        ],
        [
            2604,
            0.6989700043360189
        ]
    ],
    "non-construct": [
        [
            2059,
            0.3010299956639812
        ],
        [
            2604,
            0.47712125471966244
        ]
    ],
    "non-coop": [
        [
            474,
            0.3010299956639812
        ],
        [
            2604,
            0.47712125471966244
        ]
    ],
    "non-coron": [
        [
            1633,
            0.3010299956639812
        ],
        [
            2604,
            0.47712125471966244
        ]
    ],
    "non-credit": [
        [
            1212,
            0.3010299956639812
        ],
        [
            2604,
            0.47712125471966244
        ]
    ],
    "non-cycl": [
        [
            2362,
            0.6020599913279624
        ],
        [
            2604,
            0.8450980400142568
        ]
    ],
    "non-deict": [
        [
            2012,
            0.3010299956639812
        ],
        [
            2604,
            0.47712125471966244
        ]
    ],
    "non-deliver": [
        [
            296,
            0.47712125471966244
        ],
        [
            2604,
            0.6989700043360189
        ]
    ],
    "non-denomin": [
        [
            2604,
            0.47712125471966244
        ]
    ],
    "non-deriv": [
        [
            2015,
            0.3010299956639812
        ],
        [
            2604,
            0.47712125471966244
        ]
    ],
    "non-determin": [
        [
            2318,
            0.3010299956639812
        ],
        [
            2604,
            0.47712125471966244
        ]
    ],
    "non-educ": [
        [
            96,
            0.3010299956639812
        ],
        [
            123,
            0.3010299956639812
        ],
        [
            2604,
            0.6989700043360189
        ]
    ],
    "non-elicit": [
        [
            2547,
            0.3010299956639812
        ],
        [
            2604,
            0.47712125471966244
        ]
    ],
    "non-empir": [
        [
            956,
            0.3010299956639812
        ],
        [
            2604,
            0.47712125471966244
        ]
    ],
    "non-entail": [
        [
            1611,
            0.3010299956639812
        ],
        [
            2604,
            0.47712125471966244
        ]
    ],
    "non-exclus": [
        [
            1250,
            0.3010299956639812
        ],
        [
            1344,
            0.3010299956639812
        ],
        [
            2102,
            0.3010299956639812
        ],
        [
            2604,
            0.8450980400142568
        ]
    ],
    "non-exhaust": [
        [
            1828,
            0.3010299956639812
        ],
        [
            1949,
            0.3010299956639812
        ],
        [
            2479,
            0.3010299956639812
        ],
        [
            2604,
            0.8450980400142568
        ]
    ],
    "non-exist": [
        [
            617,
            0.3010299956639812
        ],
        [
            656,
            0.3010299956639812
        ],
        [
            660,
            0.3010299956639812
        ],
        [
            1543,
            0.47712125471966244
        ],
        [
            1582,
            0.3010299956639812
        ],
        [
            2604,
            1.1139433523068367
        ]
    ],
    "non-expert": [
        [
            1377,
            0.3010299956639812
        ],
        [
            2604,
            0.47712125471966244
        ]
    ],
    "non-explicitli": [
        [
            2271,
            0.3010299956639812
        ],
        [
            2604,
            0.47712125471966244
        ]
    ],
    "non-faculti": [
        [
            986,
            0.3010299956639812
        ],
        [
            2604,
            0.47712125471966244
        ]
    ],
    "non-finit": [
        [
            1020,
            0.3010299956639812
        ],
        [
            2604,
            0.47712125471966244
        ]
    ],
    "non-fix": [
        [
            2172,
            0.3010299956639812
        ],
        [
            2207,
            0.3010299956639812
        ],
        [
            2604,
            0.6989700043360189
        ]
    ],
    "non-focuss": [
        [
            1960,
            0.3010299956639812
        ],
        [
            2604,
            0.47712125471966244
        ]
    ],
    "non-formalist": [
        [
            1987,
            0.3010299956639812
        ],
        [
            2144,
            0.3010299956639812
        ],
        [
            2604,
            0.6989700043360189
        ]
    ],
    "non-gen": [
        [
            2402,
            0.3010299956639812
        ],
        [
            2604,
            0.47712125471966244
        ]
    ],
    "non-genet": [
        [
            846,
            0.3010299956639812
        ],
        [
            2604,
            0.47712125471966244
        ]
    ],
    "non-hachek": [
        [
            1156,
            0.3010299956639812
        ],
        [
            2604,
            0.47712125471966244
        ]
    ],
    "non-high": [
        [
            1169,
            0.6989700043360189
        ],
        [
            1356,
            0.3010299956639812
        ],
        [
            1875,
            0.3010299956639812
        ],
        [
            2604,
            1.1139433523068367
        ]
    ],
    "non-homorgan": [
        [
            1169,
            0.3010299956639812
        ],
        [
            2604,
            0.47712125471966244
        ]
    ],
    "non-human": [
        [
            786,
            0.3010299956639812
        ],
        [
            1049,
            0.6020599913279624
        ],
        [
            1106,
            0.47712125471966244
        ],
        [
            1208,
            1.0
        ],
        [
            1293,
            0.6020599913279624
        ],
        [
            1364,
            0.47712125471966244
        ],
        [
            2604,
            1.6127838567197355
        ]
    ],
    "non-ie": [
        [
            1284,
            0.47712125471966244
        ],
        [
            2604,
            0.6989700043360189
        ]
    ],
    "non-incorpor": [
        [
            1543,
            0.3010299956639812
        ],
        [
            2604,
            0.47712125471966244
        ]
    ],
    "non-increment": [
        [
            2324,
            0.3010299956639812
        ],
        [
            2413,
            0.3010299956639812
        ],
        [
            2528,
            0.3010299956639812
        ],
        [
            2604,
            0.8450980400142568
        ]
    ],
    "non-indigen": [
        [
            2419,
            0.3010299956639812
        ],
        [
            2604,
            0.47712125471966244
        ]
    ],
    "non-intent": [
        [
            2604,
            0.47712125471966244
        ]
    ],
    "non-introspect": [
        [
            2172,
            0.3010299956639812
        ],
        [
            2207,
            0.3010299956639812
        ],
        [
            2604,
            0.6989700043360189
        ]
    ],
    "non-irish": [
        [
            1188,
            0.3010299956639812
        ],
        [
            2604,
            0.47712125471966244
        ]
    ],
    "non-lawy": [
        [
            705,
            0.3010299956639812
        ],
        [
            2604,
            0.47712125471966244
        ]
    ],
    "non-leftist": [
        [
            603,
            0.3010299956639812
        ],
        [
            2604,
            0.47712125471966244
        ]
    ],
    "non-lex": [
        [
            2294,
            0.47712125471966244
        ],
        [
            2337,
            0.3010299956639812
        ],
        [
            2387,
            0.3010299956639812
        ],
        [
            2604,
            0.9542425094393249
        ]
    ],
    "non-linear": [
        [
            1307,
            0.3010299956639812
        ],
        [
            2441,
            0.3010299956639812
        ],
        [
            2604,
            0.6989700043360189
        ]
    ],
    "non-linguist": [
        [
            472,
            0.3010299956639812
        ],
        [
            531,
            0.3010299956639812
        ],
        [
            723,
            0.3010299956639812
        ],
        [
            831,
            0.3010299956639812
        ],
        [
            903,
            0.47712125471966244
        ],
        [
            914,
            0.47712125471966244
        ],
        [
            1199,
            0.6020599913279624
        ],
        [
            1271,
            0.3010299956639812
        ],
        [
            1458,
            0.3010299956639812
        ],
        [
            1869,
            0.3010299956639812
        ],
        [
            1883,
            0.3010299956639812
        ],
        [
            2085,
            0.3010299956639812
        ],
        [
            2402,
            0.7781512503836436
        ],
        [
            2435,
            0.3010299956639812
        ],
        [
            2454,
            0.3010299956639812
        ],
        [
            2604,
            1.7075701760979363
        ]
    ],
    "non-liter": [
        [
            2190,
            0.3010299956639812
        ],
        [
            2217,
            0.3010299956639812
        ],
        [
            2514,
            0.3010299956639812
        ],
        [
            2527,
            0.3010299956639812
        ],
        [
            2604,
            0.9542425094393249
        ]
    ],
    "non-literari": [
        [
            436,
            0.47712125471966244
        ],
        [
            1808,
            0.3010299956639812
        ],
        [
            2604,
            0.8450980400142568
        ]
    ],
    "non-loc": [
        [
            1930,
            0.6020599913279624
        ],
        [
            2282,
            0.3010299956639812
        ],
        [
            2437,
            0.3010299956639812
        ],
        [
            2471,
            0.3010299956639812
        ],
        [
            2506,
            0.3010299956639812
        ],
        [
            2604,
            1.1760912590556813
        ]
    ],
    "non-log": [
        [
            1206,
            0.3010299956639812
        ],
        [
            2604,
            0.47712125471966244
        ]
    ],
    "non-manu": [
        [
            1960,
            0.3010299956639812
        ],
        [
            2604,
            0.47712125471966244
        ]
    ],
    "non-memb": [
        [
            436,
            0.3010299956639812
        ],
        [
            870,
            0.47712125471966244
        ],
        [
            1403,
            0.3010299956639812
        ],
        [
            1496,
            0.3010299956639812
        ],
        [
            1784,
            0.47712125471966244
        ],
        [
            1786,
            0.3010299956639812
        ],
        [
            2148,
            0.3010299956639812
        ],
        [
            2378,
            0.47712125471966244
        ],
        [
            2389,
            0.3010299956639812
        ],
        [
            2516,
            0.3010299956639812
        ],
        [
            2526,
            0.47712125471966244
        ],
        [
            2604,
            1.5185139398778875
        ]
    ],
    "non-memori": [
        [
            2519,
            0.3010299956639812
        ],
        [
            2604,
            0.47712125471966244
        ]
    ],
    "non-merit": [
        [
            849,
            0.3010299956639812
        ],
        [
            2604,
            0.47712125471966244
        ]
    ],
    "non-met": [
        [
            913,
            0.3010299956639812
        ],
        [
            2604,
            0.47712125471966244
        ]
    ],
    "non-mod": [
        [
            1930,
            0.3010299956639812
        ],
        [
            2604,
            0.47712125471966244
        ]
    ],
    "non-monoton": [
        [
            2135,
            0.3010299956639812
        ],
        [
            2215,
            0.3010299956639812
        ],
        [
            2604,
            0.6989700043360189
        ]
    ],
    "non-mov": [
        [
            644,
            0.3010299956639812
        ],
        [
            1459,
            0.3010299956639812
        ],
        [
            1878,
            0.3010299956639812
        ],
        [
            2604,
            0.8450980400142568
        ]
    ],
    "non-n": [
        [
            572,
            0.3010299956639812
        ],
        [
            693,
            0.3010299956639812
        ],
        [
            798,
            0.3010299956639812
        ],
        [
            906,
            0.3010299956639812
        ],
        [
            915,
            0.3010299956639812
        ],
        [
            997,
            0.3010299956639812
        ],
        [
            1262,
            0.6020599913279624
        ],
        [
            1287,
            0.47712125471966244
        ],
        [
            1372,
            0.3010299956639812
        ],
        [
            1426,
            0.3010299956639812
        ],
        [
            1439,
            0.3010299956639812
        ],
        [
            1524,
            0.3010299956639812
        ],
        [
            1550,
            0.47712125471966244
        ],
        [
            1602,
            0.47712125471966244
        ],
        [
            1793,
            0.6989700043360189
        ],
        [
            1922,
            0.3010299956639812
        ],
        [
            1945,
            0.3010299956639812
        ],
        [
            2120,
            0.3010299956639812
        ],
        [
            2604,
            1.7403626894942439
        ]
    ],
    "non-nas": [
        [
            1519,
            0.3010299956639812
        ],
        [
            2604,
            0.47712125471966244
        ]
    ],
    "non-nativist": [
        [
            2454,
            0.6020599913279624
        ],
        [
            2604,
            0.8450980400142568
        ]
    ],
    "non-neutr": [
        [
            2138,
            0.3010299956639812
        ],
        [
            2604,
            0.47712125471966244
        ]
    ],
    "non-norm": [
        [
            1483,
            0.47712125471966244
        ],
        [
            2604,
            0.6989700043360189
        ]
    ],
    "non-nul": [
        [
            1459,
            0.3010299956639812
        ],
        [
            2604,
            0.47712125471966244
        ]
    ],
    "non-occurr": [
        [
            1916,
            0.3010299956639812
        ],
        [
            2604,
            0.47712125471966244
        ]
    ],
    "non-offici": [
        [
            1458,
            0.3010299956639812
        ],
        [
            2604,
            0.47712125471966244
        ]
    ],
    "non-optim": [
        [
            2138,
            0.8450980400142568
        ],
        [
            2604,
            1.1139433523068367
        ]
    ],
    "non-overt": [
        [
            1627,
            0.6020599913279624
        ],
        [
            2085,
            0.47712125471966244
        ],
        [
            2212,
            0.6989700043360189
        ],
        [
            2604,
            1.3222192947339193
        ]
    ],
    "non-parallel": [
        [
            736,
            0.3010299956639812
        ],
        [
            2604,
            0.47712125471966244
        ]
    ],
    "non-particip": [
        [
            1540,
            0.3010299956639812
        ],
        [
            1937,
            0.3010299956639812
        ],
        [
            2604,
            0.6989700043360189
        ]
    ],
    "non-past": [
        [
            1560,
            0.3010299956639812
        ],
        [
            2604,
            0.47712125471966244
        ]
    ],
    "non-perfect": [
        [
            1560,
            0.6989700043360189
        ],
        [
            2604,
            0.9542425094393249
        ]
    ],
    "non-phonolog": [
        [
            1174,
            0.3010299956639812
        ],
        [
            2604,
            0.47712125471966244
        ]
    ],
    "non-polit": [
        [
            955,
            0.3010299956639812
        ],
        [
            2604,
            0.47712125471966244
        ]
    ],
    "non-prescript": [
        [
            588,
            0.3010299956639812
        ],
        [
            2604,
            0.47712125471966244
        ]
    ],
    "non-priest": [
        [
            905,
            0.3010299956639812
        ],
        [
            937,
            0.3010299956639812
        ],
        [
            2604,
            0.6989700043360189
        ]
    ],
    "non-product": [
        [
            1358,
            0.3010299956639812
        ],
        [
            2604,
            0.47712125471966244
        ]
    ],
    "non-profit": [
        [
            286,
            0.3010299956639812
        ],
        [
            724,
            0.3010299956639812
        ],
        [
            1480,
            0.3010299956639812
        ],
        [
            2132,
            0.3010299956639812
        ],
        [
            2604,
            1.041392685158225
        ]
    ],
    "non-progress": [
        [
            1140,
            0.3010299956639812
        ],
        [
            2604,
            0.47712125471966244
        ]
    ],
    "non-proposit": [
        [
            2493,
            0.3010299956639812
        ],
        [
            2604,
            0.47712125471966244
        ]
    ],
    "non-prototyp": [
        [
            1826,
            0.3010299956639812
        ],
        [
            2604,
            0.47712125471966244
        ]
    ],
    "non-quantif": [
        [
            1842,
            0.3010299956639812
        ],
        [
            2024,
            0.3010299956639812
        ],
        [
            2604,
            0.6989700043360189
        ]
    ],
    "non-randomli": [
        [
            797,
            0.3010299956639812
        ],
        [
            2604,
            0.47712125471966244
        ]
    ],
    "non-reciproc": [
        [
            1015,
            0.3010299956639812
        ],
        [
            2604,
            0.47712125471966244
        ]
    ],
    "non-redupl": [
        [
            1358,
            0.3010299956639812
        ],
        [
            2604,
            0.47712125471966244
        ]
    ],
    "non-referenti": [
        [
            1543,
            0.47712125471966244
        ],
        [
            2604,
            0.6989700043360189
        ]
    ],
    "non-refridger": [
        [
            751,
            0.3010299956639812
        ],
        [
            2604,
            0.47712125471966244
        ]
    ],
    "non-resid": [
        [
            1552,
            0.3010299956639812
        ],
        [
            2604,
            0.47712125471966244
        ]
    ],
    "non-residenti": [
        [
            2330,
            0.47712125471966244
        ],
        [
            2604,
            0.6989700043360189
        ]
    ],
    "non-root": [
        [
            1930,
            0.3010299956639812
        ],
        [
            2604,
            0.47712125471966244
        ]
    ],
    "non-scalar": [
        [
            2387,
            0.3010299956639812
        ],
        [
            2604,
            0.47712125471966244
        ]
    ],
    "non-scientif": [
        [
            1103,
            0.3010299956639812
        ],
        [
            2604,
            0.47712125471966244
        ]
    ],
    "non-segment": [
        [
            1329,
            0.3010299956639812
        ],
        [
            2604,
            0.47712125471966244
        ]
    ],
    "non-self": [
        [
            1102,
            0.3010299956639812
        ],
        [
            2604,
            0.47712125471966244
        ]
    ],
    "non-sens": [
        [
            2604,
            0.47712125471966244
        ]
    ],
    "non-sent": [
        [
            1533,
            0.6020599913279624
        ],
        [
            2604,
            0.8450980400142568
        ]
    ],
    "non-simultan": [
        [
            1592,
            0.3010299956639812
        ],
        [
            2604,
            0.47712125471966244
        ]
    ],
    "non-smok": [
        [
            79,
            0.3010299956639812
        ],
        [
            2604,
            0.47712125471966244
        ]
    ],
    "non-snowi": [
        [
            733,
            0.3010299956639812
        ],
        [
            2604,
            0.47712125471966244
        ]
    ],
    "non-speak": [
        [
            1413,
            0.3010299956639812
        ],
        [
            2604,
            0.47712125471966244
        ]
    ],
    "non-speci": [
        [
            1364,
            0.3010299956639812
        ],
        [
            2604,
            0.47712125471966244
        ]
    ],
    "non-specialist": [
        [
            548,
            0.3010299956639812
        ],
        [
            667,
            0.3010299956639812
        ],
        [
            1011,
            0.3010299956639812
        ],
        [
            2130,
            0.3010299956639812
        ],
        [
            2362,
            0.3010299956639812
        ],
        [
            2428,
            0.3010299956639812
        ],
        [
            2515,
            0.3010299956639812
        ],
        [
            2604,
            1.2304489213782739
        ]
    ],
    "non-specif": [
        [
            736,
            0.3010299956639812
        ],
        [
            944,
            0.3010299956639812
        ],
        [
            1045,
            0.3010299956639812
        ],
        [
            1543,
            0.6020599913279624
        ],
        [
            2604,
            1.1139433523068367
        ]
    ],
    "non-speech": [
        [
            2322,
            0.3010299956639812
        ],
        [
            2604,
            0.47712125471966244
        ]
    ],
    "non-spooner": [
        [
            1171,
            0.3010299956639812
        ],
        [
            2604,
            0.47712125471966244
        ]
    ],
    "non-standard": [
        [
            527,
            0.47712125471966244
        ],
        [
            703,
            0.3010299956639812
        ],
        [
            752,
            0.3010299956639812
        ],
        [
            850,
            0.3010299956639812
        ],
        [
            1015,
            0.47712125471966244
        ],
        [
            1036,
            0.3010299956639812
        ],
        [
            1089,
            0.3010299956639812
        ],
        [
            1294,
            0.3010299956639812
        ],
        [
            1295,
            0.3010299956639812
        ],
        [
            1905,
            0.3010299956639812
        ],
        [
            2177,
            0.6020599913279624
        ],
        [
            2387,
            0.3010299956639812
        ],
        [
            2489,
            0.3010299956639812
        ],
        [
            2604,
            1.5440680443502757
        ]
    ],
    "non-statist": [
        [
            2490,
            0.3010299956639812
        ],
        [
            2604,
            0.47712125471966244
        ]
    ],
    "non-sterl": [
        [
            1766,
            0.3010299956639812
        ],
        [
            2305,
            0.3010299956639812
        ],
        [
            2604,
            0.6989700043360189
        ]
    ],
    "non-stop": [
        [
            678,
            0.3010299956639812
        ],
        [
            2604,
            0.47712125471966244
        ]
    ],
    "non-stud": [
        [
            679,
            0.3010299956639812
        ],
        [
            1736,
            0.47712125471966244
        ],
        [
            1820,
            0.3010299956639812
        ],
        [
            1931,
            0.3010299956639812
        ],
        [
            2017,
            0.3010299956639812
        ],
        [
            2078,
            0.47712125471966244
        ],
        [
            2080,
            0.3010299956639812
        ],
        [
            2105,
            0.3010299956639812
        ],
        [
            2175,
            0.47712125471966244
        ],
        [
            2243,
            0.3010299956639812
        ],
        [
            2604,
            1.5440680443502757
        ]
    ],
    "non-suffix": [
        [
            2138,
            0.3010299956639812
        ],
        [
            2604,
            0.47712125471966244
        ]
    ],
    "non-surreptiti": [
        [
            2511,
            0.3010299956639812
        ],
        [
            2604,
            0.47712125471966244
        ]
    ],
    "non-symmetr": [
        [
            599,
            0.3010299956639812
        ],
        [
            2604,
            0.47712125471966244
        ]
    ],
    "non-syntact": [
        [
            2604,
            0.6989700043360189
        ]
    ],
    "non-syntactician": [
        [
            723,
            0.3010299956639812
        ],
        [
            2604,
            0.47712125471966244
        ]
    ],
    "non-techn": [
        [
            531,
            0.3010299956639812
        ],
        [
            1780,
            0.3010299956639812
        ],
        [
            2237,
            0.3010299956639812
        ],
        [
            2238,
            0.3010299956639812
        ],
        [
            2425,
            0.3010299956639812
        ],
        [
            2604,
            1.041392685158225
        ]
    ],
    "non-tenur": [
        [
            886,
            0.3010299956639812
        ],
        [
            1316,
            0.3010299956639812
        ],
        [
            1317,
            0.3010299956639812
        ],
        [
            1335,
            0.3010299956639812
        ],
        [
            2604,
            0.9542425094393249
        ]
    ],
    "non-terminolog": [
        [
            2604,
            0.47712125471966244
        ]
    ],
    "non-text": [
        [
            2055,
            0.3010299956639812
        ],
        [
            2397,
            0.3010299956639812
        ],
        [
            2520,
            0.3010299956639812
        ],
        [
            2604,
            0.8450980400142568
        ]
    ],
    "non-tourist": [
        [
            1585,
            0.3010299956639812
        ],
        [
            2604,
            0.47712125471966244
        ]
    ],
    "non-transfer": [
        [
            1943,
            0.3010299956639812
        ],
        [
            2604,
            0.47712125471966244
        ]
    ],
    "non-trivi": [
        [
            984,
            0.3010299956639812
        ],
        [
            1793,
            0.3010299956639812
        ],
        [
            2604,
            0.8450980400142568
        ]
    ],
    "non-truth": [
        [
            1795,
            0.3010299956639812
        ],
        [
            1967,
            0.3010299956639812
        ],
        [
            2604,
            0.6989700043360189
        ]
    ],
    "non-u": [
        [
            60,
            0.3010299956639812
        ],
        [
            2604,
            0.47712125471966244
        ]
    ],
    "non-unifrom": [
        [
            1473,
            0.3010299956639812
        ],
        [
            2604,
            0.47712125471966244
        ]
    ],
    "non-valid": [
        [
            190,
            0.3010299956639812
        ],
        [
            2604,
            0.47712125471966244
        ]
    ],
    "non-verb": [
        [
            1015,
            0.3010299956639812
        ],
        [
            1441,
            0.3010299956639812
        ],
        [
            1908,
            0.3010299956639812
        ],
        [
            2185,
            0.3010299956639812
        ],
        [
            2275,
            0.3010299956639812
        ],
        [
            2352,
            0.47712125471966244
        ],
        [
            2446,
            0.47712125471966244
        ],
        [
            2604,
            1.2787536009528289
        ]
    ],
    "non-verid": [
        [
            1605,
            0.3010299956639812
        ],
        [
            1842,
            0.3010299956639812
        ],
        [
            2024,
            0.3010299956639812
        ],
        [
            2604,
            0.8450980400142568
        ]
    ],
    "non-vowel": [
        [
            691,
            0.3010299956639812
        ],
        [
            2604,
            0.47712125471966244
        ]
    ],
    "non-wel": [
        [
            2281,
            0.3010299956639812
        ],
        [
            2604,
            0.47712125471966244
        ]
    ],
    "non12": [
        [
            1196,
            0.3010299956639812
        ],
        [
            2604,
            0.47712125471966244
        ]
    ],
    "nonadult-lik": [
        [
            2604,
            0.47712125471966244
        ]
    ],
    "nonanaphor": [
        [
            1191,
            0.47712125471966244
        ],
        [
            2604,
            0.6989700043360189
        ]
    ],
    "nonaspir": [
        [
            2604,
            0.47712125471966244
        ]
    ],
    "nonbas": [
        [
            659,
            0.47712125471966244
        ],
        [
            2604,
            0.6989700043360189
        ]
    ]
}